xthread/__init__.py
xthread-0.0.2.dist-info/METADATA
xthread-0.0.2.dist-info/WHEEL
xthread-0.0.2.dist-info/licenses/LICENSE
xthread-0.0.2.dist-info/RECORD
