Metadata-Version: 2.1
Name: xthread
Version: 0.0.2
Summary: Useful threading for pause/unpause and terminating
Project-URL: Homepage, https://github.com/magiskboy/xthread
Project-URL: Documentation, https://github.com/magiskboy/xthread#features
Project-URL: Issues, https://github.com/magiskboy/xthread/issues/
Project-URL: Source, https://github.com/magiskboy/xthread
Project-URL: Changelog, https://github.com/magiskboy/xthread/blob/main/CHANGELOG.md
Author-email: Nguyen Khac Thanh <nguyenkhacthanh244@gmail.com>
License-Expression: MIT
License-File: LICENSE
Keywords: thread,threading
Classifier: Development Status :: 3 - Alpha
Classifier: Intended Audience :: Developers
Classifier: License :: OSI Approved :: MIT License
Classifier: Operating System :: OS Independent
Classifier: Programming Language :: Python :: 3.7
Classifier: Programming Language :: Python :: 3.8
Classifier: Programming Language :: Python :: 3.9
Classifier: Programming Language :: Python :: 3.10
Classifier: Programming Language :: Python :: 3.11
Requires-Python: >=3.7
Provides-Extra: dev
Requires-Dist: coverage; extra == 'dev'
Requires-Dist: mypy; extra == 'dev'
Requires-Dist: ruff; extra == 'dev'
